matplot_flex/__init__.py
matplot_flex/axes_utils.py
matplot_flex/config.py
matplot_flex/decorators.py
matplot_flex/layout.py
matplot_flex/renderers.py
matplot_flex/templates.py
matplot_flex/text_utils.py
matplot_flex-0.2.0.dist-info/licenses/LICENSE
matplot_flex-0.2.0.dist-info/METADATA
matplot_flex-0.2.0.dist-info/WHEEL
matplot_flex-0.2.0.dist-info/top_level.txt
matplot_flex-0.2.0.dist-info/RECORD
