Metadata-Version: 2.4
Name: matplot-flex
Version: 0.2.0
Summary: Modular matplotlib plotting helpers
Author: obitsu-jo
License: MIT License
Project-URL: Homepage, https://github.com/obitsu-jo/matplot-flex
Project-URL: Source, https://github.com/obitsu-jo/matplot-flex
Project-URL: Issues, https://github.com/obitsu-jo/matplot-flex/issues
Classifier: License :: OSI Approved :: MIT License
Classifier: Programming Language :: Python :: 3
Classifier: Programming Language :: Python :: 3.10
Classifier: Programming Language :: Python :: 3.11
Classifier: Programming Language :: Python :: 3.12
Classifier: Operating System :: OS Independent
Requires-Python: >=3.10
License-File: LICENSE
Requires-Dist: matplotlib<4,>=3.8
Requires-Dist: numpy<2,>=1.26
Provides-Extra: dev
Requires-Dist: pytest; extra == "dev"
Requires-Dist: build; extra == "dev"
Requires-Dist: twine; extra == "dev"
Dynamic: license-file
